streamsx/sttgateway/__init__.py
streamsx/sttgateway/_sttgateway.py
streamsx/sttgateway/schema.py
streamsx.sttgateway-1.0.1.dist-info/LICENSE.txt
streamsx.sttgateway-1.0.1.dist-info/METADATA
streamsx.sttgateway-1.0.1.dist-info/WHEEL
streamsx.sttgateway-1.0.1.dist-info/top_level.txt
streamsx.sttgateway-1.0.1.dist-info/RECORD
