Metadata-Version: 2.1
Name: streamsx.sttgateway
Version: 1.0.1
Summary: Speech To Text gateway integration for IBM Streams
Home-page: https://github.com/IBMStreams/pypi.streamsx.sttgateway
Author: IBM Streams @ github.com
Author-email: hegermar@de.ibm.com
License: Apache License - Version 2.0
Keywords: streams,ibmstreams,streaming,analytics,streaming-analytics,sttgateway
Platform: UNKNOWN
Classifier: Development Status :: 1 - Planning
Classifier: License :: OSI Approved :: Apache Software License
Classifier: Programming Language :: Python :: 3
Classifier: Programming Language :: Python :: 3.5
Classifier: Programming Language :: Python :: 3.6
Classifier: Programming Language :: Python :: 3.7
Requires-Dist: streamsx (>=1.14.6)
Requires-Dist: streamsx.toolkits
